OmniEvent/__init__.py
OmniEvent/arguments.py
OmniEvent/infer.py
OmniEvent/trainer.py
OmniEvent/trainer_seq2seq.py
OmniEvent/utils.py
OmniEvent/aggregation/__init__.py
OmniEvent/aggregation/aggregation.py
OmniEvent/backbone/__init__.py
OmniEvent/backbone/backbone.py
OmniEvent/evaluation/__init__.py
OmniEvent/evaluation/convert_format.py
OmniEvent/evaluation/dump_result.py
OmniEvent/evaluation/metric.py
OmniEvent/evaluation/utils.py
OmniEvent/head/__init__.py
OmniEvent/head/classification.py
OmniEvent/head/crf.py
OmniEvent/head/head.py
OmniEvent/infer_module/__init__.py
OmniEvent/infer_module/io_format.py
OmniEvent/infer_module/seq2seq.py
OmniEvent/input_engineering/__init__.py
OmniEvent/input_engineering/base_processor.py
OmniEvent/input_engineering/input_utils.py
OmniEvent/input_engineering/mrc_converter.py
OmniEvent/input_engineering/mrc_processor.py
OmniEvent/input_engineering/seq2seq_processor.py
OmniEvent/input_engineering/sequence_labeling_processor.py
OmniEvent/input_engineering/token_classification_processor.py
OmniEvent/input_engineering/tokenizer.py
OmniEvent/input_engineering/whitespace_tokenizer.py
OmniEvent/model/__init__.py
OmniEvent/model/constraint_decoding.py
OmniEvent/model/label_smoother_sum.py
OmniEvent/model/model.py
OmniEvent-0.1.7.dist-info/LICENSE
OmniEvent-0.1.7.dist-info/METADATA
OmniEvent-0.1.7.dist-info/WHEEL
OmniEvent-0.1.7.dist-info/top_level.txt
OmniEvent-0.1.7.dist-info/RECORD
