Metadata-Version: 2.1
Name: OmniEvent
Version: 0.1.7
Summary: A tookit for event extraction.
License: Copyright (c) 2022 THUKEG
Project-URL: Homepage, https://github.com/THU-KEG/OmniEvent
Project-URL: Bug Tracker, https://github.com/THU-KEG/OmniEvent/issues
Classifier: Programming Language :: Python :: 3
Classifier: License :: OSI Approved :: MIT License
Classifier: Operating System :: OS Independent
Requires-Python: >=3.7
License-File: LICENSE
Requires-Dist: scikit-learn (==1.0.2)
Requires-Dist: six (==1.16.0)
Requires-Dist: transformers (==4.21.2)
Requires-Dist: sentencepiece (==0.1.97)
Requires-Dist: seqeval (==1.2.2)
Requires-Dist: protobuf (==3.20.1)
Requires-Dist: deepspeed (==0.7.2)
Requires-Dist: jsonlines (==3.1.0)
Requires-Dist: pyyaml (==6.0)
